cubi_isa_templates/__init__.py
cubi_isa_templates/_version.py
cubi_isa_templates/isatab-bulk_rnaseq/cookiecutter.json
cubi_isa_templates/isatab-bulk_rnaseq/{{cookiecutter.__output_dir}}/a_{{cookiecutter.assay_prefix}}_{{cookiecutter.assay_name}}.txt
cubi_isa_templates/isatab-bulk_rnaseq/{{cookiecutter.__output_dir}}/i_Investigation.txt
cubi_isa_templates/isatab-bulk_rnaseq/{{cookiecutter.__output_dir}}/s_{{cookiecutter.s_file_name}}.txt
cubi_isa_templates/isatab-generic/cookiecutter.json
cubi_isa_templates/isatab-generic/{{cookiecutter.__output_dir}}/.~lock.s_{{cookiecutter.s_file_name}}.txt#
cubi_isa_templates/isatab-generic/{{cookiecutter.__output_dir}}/a_{{cookiecutter.assay_prefix}}_{{cookiecutter.assay_name}}.txt
cubi_isa_templates/isatab-generic/{{cookiecutter.__output_dir}}/i_Investigation.txt
cubi_isa_templates/isatab-generic/{{cookiecutter.__output_dir}}/s_{{cookiecutter.s_file_name}}.txt
cubi_isa_templates/isatab-germline/cookiecutter.json
cubi_isa_templates/isatab-germline/{{cookiecutter.__output_dir}}/a_{{cookiecutter.s_file_name}}_{{cookiecutter.__assay_name}}.txt
cubi_isa_templates/isatab-germline/{{cookiecutter.__output_dir}}/i_Investigation.txt
cubi_isa_templates/isatab-germline/{{cookiecutter.__output_dir}}/s_{{cookiecutter.s_file_name}}.txt
cubi_isa_templates/isatab-mass_cytometry/cookiecutter.json
cubi_isa_templates/isatab-mass_cytometry/{{cookiecutter.__output_dir}}/a_{{cookiecutter.__assay_prefix}}_mass_cytometry.txt
cubi_isa_templates/isatab-mass_cytometry/{{cookiecutter.__output_dir}}/i_Investigation.txt
cubi_isa_templates/isatab-mass_cytometry/{{cookiecutter.__output_dir}}/s_{{cookiecutter.__s_file_name}}.txt
cubi_isa_templates/isatab-microarray/cookiecutter.json
cubi_isa_templates/isatab-microarray/{{cookiecutter.__output_dir}}/a_{{cookiecutter.assay_prefix}}_{{cookiecutter.assay_name}}.txt
cubi_isa_templates/isatab-microarray/{{cookiecutter.__output_dir}}/i_investigation.txt
cubi_isa_templates-0.1.2.dist-info/LICENSE
cubi_isa_templates-0.1.2.dist-info/METADATA
cubi_isa_templates-0.1.2.dist-info/WHEEL
cubi_isa_templates-0.1.2.dist-info/top_level.txt
cubi_isa_templates-0.1.2.dist-info/RECORD
