Metadata-Version: 2.1
Name: cubi-isa-templates
Version: 0.1.2
Summary: CUBI ISA-Tab templates
Home-page: https://github.com/bihealth/cubi-isa-templates
Author: Berlin Institute of Health, Core Unit Bioinformatics
Author-email: cubi@bih-charite.de
License: MIT license
Project-URL: Changelog, https://github.com/bihealth/cubi-isa-templates/blob/main/CHANGELOG.md
Classifier: Intended Audience :: Developers
Classifier: License :: OSI Approved :: MIT License
Classifier: Natural Language :: English
Classifier: Topic :: Scientific/Engineering :: Bio-Informatics
Classifier: Programming Language :: Python :: 3
Classifier: Programming Language :: Python :: 3.8
Classifier: Programming Language :: Python :: 3.9
Classifier: Programming Language :: Python :: 3.10
Classifier: Programming Language :: Python :: 3.11
License-File: LICENSE
Requires-Dist: attrs
